LICENSE
MANIFEST.in
README.md
setup.cfg
setup.py
./aegis/__init__.py
./aegis/alpaca/__init__.py
./aegis/alpaca/utils.py
./aegis/charts/__init__.py
./aegis/charts/bounds.py
./aegis/charts/indicators.py
./aegis/charts/shapes.py
./aegis/charts/trend.py
./aegis/charts/utils.py
./aegis/debt/__init__.py
./aegis/debt/utils.py
./aegis/equity/__init__.py
./aegis/equity/accounting.py
./aegis/equity/growth.py
./aegis/equity/risk.py
./aegis/equity/stats.py
./aegis/equity/utils.py
./aegis/equity/valuation.py
./aegis/macro/__init__.py
./aegis/macro/endpoints.py
./aegis/macro/gdp.py
./aegis/macro/labour.py
./aegis/macro/price.py
./aegis/macro/trade.py
./aegis/macro/utils.py
./aegis/plot/__init__.py
./aegis/plot/utils.py
aegis_engine.egg-info/PKG-INFO
aegis_engine.egg-info/SOURCES.txt
aegis_engine.egg-info/dependency_links.txt
aegis_engine.egg-info/requires.txt
aegis_engine.egg-info/top_level.txt