Metadata-Version: 2.1
Name: aegis-engine
Version: 1.0.7
Summary: Capital market asset valuation engine.
Home-page: https://github.com/itchysnake/aegis
Author: Bailey de Villiers
Author-email: bailey.devilliers@gmail.com
License: MIT
License-File: LICENSE
